clihelperjk/__init__.py
clihelperjk/__main__.py
clihelperjk/office.py
clihelperjk-1.0.2.dist-info/licenses/LICENSE
clihelperjk-1.0.2.dist-info/METADATA
clihelperjk-1.0.2.dist-info/WHEEL
clihelperjk-1.0.2.dist-info/entry_points.txt
clihelperjk-1.0.2.dist-info/top_level.txt
clihelperjk-1.0.2.dist-info/RECORD
