Metadata-Version: 2.4
Name: clihelperjk
Version: 1.0.2
Summary: CLI interactivo para administrar Microsoft Office 2016/2019/2021
Home-page: 
Author: Juan Kraudy
Author-email: 
License: MIT
Classifier: Programming Language :: Python :: 3
Classifier: Operating System :: Microsoft :: Windows
Classifier: Topic :: Utilities
Requires-Python: >=3.6
License-File: LICENSE
Dynamic: author
Dynamic: classifier
Dynamic: description
Dynamic: description-content-type
Dynamic: license
Dynamic: license-file
Dynamic: requires-python
Dynamic: summary
